interactive_dependency_resolver.py
interactive_dependency_resolver-0.1.0a1.dist-info/licenses/LICENSE
interactive_dependency_resolver-0.1.0a1.dist-info/METADATA
interactive_dependency_resolver-0.1.0a1.dist-info/WHEEL
interactive_dependency_resolver-0.1.0a1.dist-info/top_level.txt
interactive_dependency_resolver-0.1.0a1.dist-info/RECORD
