Metadata-Version: 2.4
Name: interactive-dependency-resolver
Version: 0.1.0a1
Summary: A tool to interactively resolve Python wheel dependencies.
Author-email: Jifeng Wu <jifengwu2k@gmail.com>
License-Expression: AGPL-3.0
Project-URL: Homepage, https://github.com/jifengwu2k/interactive-dependency-resolver
Project-URL: Bug Tracker, https://github.com/jifengwu2k/interactive-dependency-resolver/issues
Classifier: Programming Language :: Python :: 2
Classifier: Programming Language :: Python :: 3
Classifier: Operating System :: OS Independent
Requires-Python: >=2
License-File: LICENSE
Requires-Dist: packaging
Requires-Dist: python-dateutil
Requires-Dist: sortedcontainers
Requires-Dist: textcompat
Dynamic: license-file
